setup.py
akbase2233/AKbase2233.py
akbase2233/__init__.py
akbase2233.egg-info/PKG-INFO
akbase2233.egg-info/SOURCES.txt
akbase2233.egg-info/dependency_links.txt
akbase2233.egg-info/top_level.txt