Metadata-Version: 1.0
Name: akbase2233
Version: 0.1.2
Summary: use you self password table, encrypt and decrypt you content
Home-page: UNKNOWN
Author: Kuture
Author-email: kuture@163.com
License: MIT Licence
Keywords: pip,akbase2233,base,timetool,kuture,encrypt,decrypt,base2233,akbase
Platform: any
